{"elements":[{"from":[1.1428566,8.0,1.1428566],"to":[14.857143,8.0,14.857143],"rotation":{"angle":0.0,"axis":"y","origin":[8.0,8.0,8.0]},"faces":{"east":{"uv":[0.0,0.0,0.0,6.0],"rotation":90,"texture":"#0","tintindex":0},"south":{"uv":[6.0,0.0,0.0,0.0],"rotation":0,"texture":"#0","tintindex":0},"north":{"uv":[6.0,0.0,0.0,0.0],"rotation":180,"texture":"#0","tintindex":0},"west":{"uv":[0.0,0.0,0.0,6.0],"rotation":270,"texture":"#0","tintindex":0},"up":{"uv":[0.0,6.0,6.0,12.0],"rotation":0,"texture":"#0","tintindex":0},"down":{"uv":[0.0,0.0,6.0,6.0],"rotation":180,"texture":"#0","tintindex":0}}},{"from":[1.1428566,8.0,1.1428566],"to":[14.857143,8.0,14.857143],"rotation":{"angle":0.0,"axis":"y","origin":[8.0,8.0,8.0]},"faces":{"east":{"uv":[0.0,0.0,0.0,6.0],"rotation":90,"texture":"#0","tintindex":0},"south":{"uv":[6.0,0.0,0.0,0.0],"rotation":0,"texture":"#0","tintindex":0},"north":{"uv":[6.0,0.0,0.0,0.0],"rotation":180,"texture":"#0","tintindex":0},"west":{"uv":[0.0,0.0,0.0,6.0],"rotation":270,"texture":"#0","tintindex":0},"up":{"uv":[0.0,6.0,6.0,12.0],"rotation":0,"texture":"#0","tintindex":0},"down":{"uv":[0.0,0.0,6.0,6.0],"rotation":180,"texture":"#0","tintindex":0}}}],"textures":{"0":"modelengine:entity/gm_galaxy_dragon_galax01"},"display":{"head":{"translation":[0.0,-6.4,0.0],"scale":[4.0,4.0,4.0]}}}